mcp_tinybird/__init__.py
mcp_tinybird/__main__.py
mcp_tinybird/run_sse.py
mcp_tinybird/run_stdio.py
mcp_tinybird/server.py
mcp_tinybird/sse.py
mcp_tinybird/stdio.py
mcp_tinybird/tb.py
iflow_mcp_mcp_tinybird-1.0.2.dist-info/METADATA
iflow_mcp_mcp_tinybird-1.0.2.dist-info/WHEEL
iflow_mcp_mcp_tinybird-1.0.2.dist-info/entry_points.txt
iflow_mcp_mcp_tinybird-1.0.2.dist-info/licenses/LICENSE
iflow_mcp_mcp_tinybird-1.0.2.dist-info/RECORD
