Metadata-Version: 2.4
Name: iflow-mcp_mcp-tinybird
Version: 1.0.2
Summary: An MCP server to interact with a Tinybird Workspace from any MCP client.
Project-URL: homepage, https://github.com/tinybirdco/mcp-tinybird
Author-email: alrocar <alrocar@tinybird.co>
License-File: LICENSE
Requires-Python: >=3.10
Requires-Dist: httpx>=0.27.2
Requires-Dist: mcp>=1.0.0
Requires-Dist: python-dotenv>=1.0.1
Requires-Dist: starlette>=0.36.0
Requires-Dist: tinybird-python-sdk>=0.1.6
Requires-Dist: uvicorn>=0.27.0
Provides-Extra: dev
Requires-Dist: black>=23.12.1; extra == 'dev'
Requires-Dist: pyproject-toml>=0.0.10; extra == 'dev'
